[{"__type__":"cc.SpriteFrame","content":{"name":"20864","texture":"6d60FNEgxDWqCjERAtlcbW","rect":[536,614,498,159],"offset":[0,1],"originalSize":[500,161],"capInsets":[0,0,0,0]}},{"__type__":"cc.SpriteFrame","content":{"name":"20773","texture":"6d60FNEgxDWqCjERAtlcbW","rect":[1748,392,430,206],"offset":[0,1],"originalSize":[432,208],"rotated":1,"capInsets":[0,0,0,0]}},{"__type__":"cc.SpriteFrame","content":{"name":"20882","texture":"6d60FNEgxDWqCjERAtlcbW","rect":[975,1208,400,328],"offset":[0,1],"originalSize":[402,330],"capInsets":[0,0,0,0]}},{"__type__":"cc.SpriteFrame","content":{"name":"20885","texture":"6d60FNEgxDWqCjERAtlcbW","rect":[739,1566,427,545],"offset":[0,1],"originalSize":[429,547],"rotated":1,"capInsets":[0,0,0,0]}},{"__type__":"cc.SpriteFrame","content":{"name":"20916","texture":"6d60FNEgxDWqCjERAtlcbW","rect":[536,775,442,357],"offset":[0,1],"originalSize":[444,359],"capInsets":[0,0,0,0]}},{"__type__":"cc.SpriteFrame","content":{"name":"20933","texture":"6d60FNEgxDWqCjERAtlcbW","rect":[1748,2,274,388],"offset":[0,1],"originalSize":[276,390],"capInsets":[0,0,0,0]}},{"__type__":"cc.SpriteFrame","content":{"name":"20915","texture":"6d60FNEgxDWqCjERAtlcbW","rect":[1719,824,422,327],"offset":[0,1],"originalSize":[424,329],"rotated":1,"capInsets":[0,0,0,0]}},{"__type__":"cc.SpriteFrame","content":{"name":"20897","texture":"6d60FNEgxDWqCjERAtlcbW","rect":[536,1134,437,430],"offset":[0,1],"originalSize":[439,432],"capInsets":[0,0,0,0]}},{"__type__":"cc.SpriteFrame","content":{"name":"20903","texture":"6d60FNEgxDWqCjERAtlcbW","rect":[1377,1208,359,327],"offset":[0,1],"originalSize":[361,329],"rotated":1,"capInsets":[0,0,0,0]}},{"__type__":"cc.SpriteFrame","content":{"name":"20890","texture":"6d60FNEgxDWqCjERAtlcbW","rect":[1286,1569,401,389],"offset":[0,1],"originalSize":[403,391],"rotated":1,"capInsets":[0,0,0,0]}},{"__type__":"cc.SpriteAtlas","_name":"xuedi4.plist","_spriteFrames":{"20773":{"__uuid__":"10ghXWQlxIHo7DIvlptatH"},"20864":{"__uuid__":"0bIdtfEWNBg5GYTCv8xUOs"},"20865":{"__uuid__":"bfMq3uAmFNX7eJkIvZ2ijz"},"20866":{"__uuid__":"b8jyRQDWtEYay+glI9Xbml"},"20877":{"__uuid__":"ffdk7ZYvxDibZheNxWXlML"},"20882":{"__uuid__":"1fVZNdBwdBOY288yMvoXZK"},"20885":{"__uuid__":"29kVPi7dFBTqWJpViCbwtK"},"20888":{"__uuid__":"b4lNa2XmtJV41JvFc+2d0N"},"20890":{"__uuid__":"96f0IUJhRNGKmNZ/LHQHC6"},"20897":{"__uuid__":"8cRZ5yCqVFBYgn3WJtUuAa"},"20902":{"__uuid__":"df4lN2Ni5GDa0X4DTjbYc9"},"20903":{"__uuid__":"8c52aMOVNK2aUQY5LVb5rL"},"20915":{"__uuid__":"74gVD/LltGC4lwyix8+JgG"},"20916":{"__uuid__":"32ojORohBKOaayVGLjbxpy"},"20933":{"__uuid__":"69akr0qL1MJrK3a84NMQmT"},"20935":{"__uuid__":"baxqJvxc5ADaZNrX24nHbv"}}},{"__type__":"cc.SpriteFrame","content":{"name":"20888","texture":"6d60FNEgxDWqCjERAtlcbW","rect":[1051,560,666,646],"offset":[0,1],"originalSize":[668,648],"capInsets":[0,0,0,0]}},{"__type__":"cc.SpriteFrame","content":{"name":"20866","texture":"6d60FNEgxDWqCjERAtlcbW","rect":[2,614,532,592],"offset":[0,1],"originalSize":[534,594],"capInsets":[0,0,0,0]}},{"__type__":"cc.SpriteFrame","content":{"name":"20935","texture":"6d60FNEgxDWqCjERAtlcbW","rect":[2,1248,655,374],"offset":[0,1],"originalSize":[657,376],"rotated":1,"capInsets":[0,0,0,0]}},{"__type__":"cc.SpriteFrame","content":{"name":"20865","texture":"6d60FNEgxDWqCjERAtlcbW","rect":[1051,2,695,556],"offset":[0,1],"originalSize":[697,558],"capInsets":[0,0,0,0]}},{"__type__":"cc.SpriteFrame","content":{"name":"20902","texture":"6d60FNEgxDWqCjERAtlcbW","rect":[378,1566,359,429],"offset":[0,1],"originalSize":[361,431],"capInsets":[0,0,0,0]}},{"__type__":"cc.SpriteFrame","content":{"name":"20877","texture":"6d60FNEgxDWqCjERAtlcbW","rect":[2,2,1047,610],"offset":[0,1],"originalSize":[1049,612],"capInsets":[0,0,0,0]}}]